yosafe_packages/yosafe_subpackage_1/__init__.py
yosafe_packages/yosafe_subpackage_1/yosafe_subpackage_1_functions.py
yosafe_packages/yosafe_subpackage_1/yosafe_subpackage_1_functions_2.py
yosafe_subpackage_1-0.1.3.dist-info/METADATA
yosafe_subpackage_1-0.1.3.dist-info/WHEEL
yosafe_subpackage_1-0.1.3.dist-info/RECORD
